gaeconf/__init__.py
gaeconf/cli.py
gaeconf/gaeconf.py
gaeconf-0.1.3.dist-info/AUTHORS.rst
gaeconf-0.1.3.dist-info/LICENSE
gaeconf-0.1.3.dist-info/METADATA
gaeconf-0.1.3.dist-info/WHEEL
gaeconf-0.1.3.dist-info/entry_points.txt
gaeconf-0.1.3.dist-info/top_level.txt
gaeconf-0.1.3.dist-info/RECORD
