Metadata-Version: 2.1
Name: gaeconf
Version: 0.1.3
Summary: CLI utility to generate .yaml GAE configurations
Home-page: https://gitlab.com/emailmeter-foss/gaeconf
Author: ShuttleCloud Corp
Author-email: team@emailmeter.com
License: MIT license
Keywords: gaeconf
Platform: UNKNOWN
Classifier: Development Status :: 4 - Beta
Classifier: Intended Audience :: Developers
Classifier: License :: OSI Approved :: MIT License
Classifier: Natural Language :: English
Classifier: Programming Language :: Python :: 3.7
Requires-Dist: Click (>=6.0)
Requires-Dist: ruamel.yaml (>=0.15.97)
